CHANGELOG
MANIFEST.in
README.txt
sendmail.py
setup.py
sendmail.egg-info/PKG-INFO
sendmail.egg-info/SOURCES.txt
sendmail.egg-info/dependency_links.txt
sendmail.egg-info/top_level.txt