Metadata-Version: 1.1
Name: sendmail
Version: 2.0
Summary: Send a message by invoking '/usr/sbin/sendmail' program
Home-page: http://www.ultimate.com/phil/python/#sendmail
Author: Phil Budne
Author-email: phil@ultimate.com
License: MIT
Download-URL: http://www.ultimate.com/phil/python/download/sendmail-2.0.tar.gz
Platform: POSIX
Classifier: Development Status :: 5 - Production/Stable
Classifier: Intended Audience :: Developers
Classifier: License :: OSI Approved :: MIT License
Classifier: Operating System :: POSIX
Classifier: Programming Language :: Python :: 2.7
Classifier: Programming Language :: Python :: 3
Classifier: Topic :: Internet
Classifier: Topic :: Communications :: Email
Classifier: Topic :: Software Development :: Libraries :: Python Modules
